rest_framework_recursive/__init__.py
rest_framework_recursive/fields.py
djangorestframework_recursive-0.1.1.dist-info/METADATA
djangorestframework_recursive-0.1.1.dist-info/RECORD
djangorestframework_recursive-0.1.1.dist-info/metadata.json
djangorestframework_recursive-0.1.1.dist-info/top_level.txt
djangorestframework_recursive-0.1.1.dist-info/DESCRIPTION.rst
djangorestframework_recursive-0.1.1.dist-info/WHEEL
