Metadata-Version: 2.0
Name: djangorestframework-recursive
Version: 0.1.1
Summary: Recursive Serialization for Django REST framework
Home-page: https://github.com/heywbj/django-rest-framework-recursive
Author: Warren Jin
Author-email: jinwarren@gmail.com
License: BSD
Platform: UNKNOWN
Classifier: Development Status :: 2 - Pre-Alpha
Classifier: Environment :: Web Environment
Classifier: Framework :: Django
Classifier: Intended Audience :: Developers
Classifier: License :: OSI Approved :: BSD License
Classifier: Operating System :: OS Independent
Classifier: Natural Language :: English
Classifier: Programming Language :: Python :: 2
Classifier: Programming Language :: Python :: 2.7
Classifier: Programming Language :: Python :: 3
Classifier: Programming Language :: Python :: 3.3
Classifier: Programming Language :: Python :: 3.4
Classifier: Topic :: Internet :: WWW/HTTP
Requires-Dist: Django
Requires-Dist: djangorestframework (>=3.0)
